__init__.py
imagedata_registration/__init__.py
imagedata_registration/Elastix/__init__.py
imagedata_registration/FSL/__init__.py
imagedata_registration/NPreg/multigrid_nonlin_cy.pyx
imagedata_registration/NPreg/multigrid_nonlin.py
imagedata_registration/NPreg/multigrid_nonlin_cupy.py
imagedata_registration/NPreg/translate_image.py
imagedata_registration/NPreg/multigrid_nonlin_cy.cpython-311-darwin.so
imagedata_registration/NPreg/multilevel.py
imagedata_registration/NPreg/Makefile
imagedata_registration/NPreg/navlam_nonlinear_highlevel.py
imagedata_registration/NPreg/getcost.py
imagedata_registration/NPreg/__init__.py
imagedata_registration/NPreg/gradientreg.py
imagedata_registration/NPreg/normgrad.py
imagedata_registration/NPreg/navlam_nonlinear_3.py
imagedata_registration/NPreg/centergrid.py
imagedata_registration/NPreg/resize.py
imagedata_registration/NPreg/transform.py
imagedata_registration/NPreg/navlam_nonlinear_lowlevel.py
imagedata_registration/NPreg/npreg_cy.py
imagedata_registration/NPreg/navlam_nonlinear_highlevel_opt.py
imagedata_registration/NPreg/cells.py
imagedata_registration/NPreg/multigrid_nonlin_highlevel.py
imagedata_registration/NPreg/scale.py
imagedata_registration/NPreg/navlam_nonlinear_highlevel_cupy.py
imagedata_registration/NPreg/multigrid_nonlin_cc.pyx
imagedata_registration-0.3.6.dist-info/RECORD
imagedata_registration-0.3.6.dist-info/WHEEL
imagedata_registration-0.3.6.dist-info/top_level.txt
imagedata_registration-0.3.6.dist-info/METADATA
imagedata_registration-0.3.6.dist-info/licenses/LICENSE
