Metadata-Version: 2.4
Name: imagedata-registration
Version: 0.3.6
Summary: Image registration routines for Imagedata
Author-email: Erling Andersen <Erling.Andersen@Helse-Bergen.NO>, Erlend Hodneland <Erlend.Hodneland@uib.no>
Maintainer-email: Erling Andersen <Erling.Andersen@Helse-Bergen.NO>
License: MIT License
Project-URL: Documentation, https://imagedata_registration.readthedocs.io
Project-URL: SourceCode, https://github.com/erling6232/imagedata_registration
Project-URL: Changelog, https://github.com/erling6232/imagedata_registration/CHANGELOG.rst
Keywords: python,medical,imaging,image registration
Classifier: Programming Language :: Python :: 3
Classifier: Development Status :: 4 - Beta
Classifier: Environment :: Other Environment
Classifier: Intended Audience :: Developers
Classifier: Intended Audience :: Healthcare Industry
Classifier: Intended Audience :: Science/Research
Classifier: License :: OSI Approved :: MIT License
Classifier: Operating System :: OS Independent
Classifier: Topic :: Software Development :: Libraries :: Python Modules
Classifier: Topic :: Scientific/Engineering :: Medical Science Apps.
Requires-Python: <3.14,>=3.9
License-File: LICENSE
Requires-Dist: setuptools
Requires-Dist: cython
Requires-Dist: itk-elastix
Requires-Dist: imagedata<3.9,>=3.8.0
Dynamic: license-file
